fakeset/__init__.py
fakeset/generator.py
fakeset-0.0.2.dist-info/LICENSE
fakeset-0.0.2.dist-info/METADATA
fakeset-0.0.2.dist-info/WHEEL
fakeset-0.0.2.dist-info/top_level.txt
fakeset-0.0.2.dist-info/RECORD
