Metadata-Version: 2.1
Name: fakeset
Version: 0.0.2
Summary: Fake Dataset
Home-page: https://github.com/JiauZhang/fakeset
Author: JiauZhang
Author-email: jiauzhang@163.com
License: MIT
Keywords: Deep Learning,Fake Dataset,Artificial Intelligence
Classifier: Intended Audience :: Developers
Classifier: Topic :: Scientific/Engineering :: Artificial Intelligence
Classifier: License :: OSI Approved :: MIT License
Classifier: Programming Language :: Python :: 3.8
License-File: LICENSE
Requires-Dist: numpy >=1.19.5
